mtnlion/__init__.py
mtnlion/assemblers.py
mtnlion/cli.py
mtnlion/deprecated_domain.py
mtnlion/domain.py
mtnlion/element.py
mtnlion/engine.py
mtnlion/formula.py
mtnlion/model.py
mtnlion/mtnlion.py
mtnlion/problem_space.py
mtnlion/report.py
mtnlion/solution.py
mtnlion/formulas/__init__.py
mtnlion/formulas/approximation.py
mtnlion/formulas/dfn.py
mtnlion/formulas/time_integration.py
mtnlion/models/__init__.py
mtnlion/models/double_layer.py
mtnlion/models/lithium_plating.py
mtnlion/models/newman_isothermal.py
mtnlion/models/newman_isothermal_dae.py
mtnlion/models/sei.py
mtnlion/newman/__init__.py
mtnlion/newman/equations.py
mtnlion/structures/__init__.py
mtnlion/structures/mountain.py
mtnlion/tools/__init__.py
mtnlion/tools/cache.py
mtnlion/tools/comsol.py
mtnlion/tools/helpers.py
mtnlion/tools/ldp.py
mtnlion/tools/loader.py
mtnlion-0.0.1.dist-info/AUTHORS.rst
mtnlion-0.0.1.dist-info/LICENSE
mtnlion-0.0.1.dist-info/METADATA
mtnlion-0.0.1.dist-info/WHEEL
mtnlion-0.0.1.dist-info/entry_points.txt
mtnlion-0.0.1.dist-info/top_level.txt
mtnlion-0.0.1.dist-info/RECORD
