Metadata-Version: 2.1
Name: mtnlion
Version: 0.0.1
Summary: Mountain Lion Continuum-Scale Lithium-Ion Cell Simulator uses FEniCS to solve partial differential equations for the internal states of Lithium-Ion cells.
Home-page: https://gitlab.com/macklenc/mtnlion
Author: Christopher Macklen
Author-email: cmacklen@uccs.edu
License: MIT license
Keywords: mtnlion
Platform: UNKNOWN
Classifier: Development Status :: 4 - Beta
Classifier: Intended Audience :: Science/Research
Classifier: License :: OSI Approved :: MIT License
Classifier: Natural Language :: English
Classifier: Programming Language :: Python :: 3.6
Requires-Python: >=3.6
Requires-Dist: fenics (==2018.1.0)
Requires-Dist: Click
Requires-Dist: numpy
Requires-Dist: matplotlib
Requires-Dist: munch
Requires-Dist: scipy
Requires-Dist: xlrd
Requires-Dist: sympy
